glean_mcp/__init__.py
glean_mcp/_cli.py
glean_mcp/cookie_client.py
glean_mcp/glean_filter.py
glean_mcp/py.typed
glean_mcp/server.py
glean_mcp/test_support.py
glean_mcp/token_client.py
glean_mcp-3.3.0.dist-info/licenses/LICENSE
glean_mcp-3.3.0.dist-info/METADATA
glean_mcp-3.3.0.dist-info/WHEEL
glean_mcp-3.3.0.dist-info/entry_points.txt
glean_mcp-3.3.0.dist-info/top_level.txt
glean_mcp-3.3.0.dist-info/RECORD
