Metadata-Version: 2.4
Name: glean-mcp
Version: 3.3.0
Summary: Python client + MCP server adapter for Glean (search, chat, read documents). Provides a reusable HTTP client plus simple sync helper functions.
Author: Alan Shum
License-Expression: MIT
Project-URL: Homepage, https://github.com/alankyshum/glean-mcp-server
Project-URL: Repository, https://github.com/alankyshum/glean-mcp-server
Project-URL: Issues, https://github.com/alankyshum/glean-mcp-server/issues
Project-URL: Changelog, https://github.com/alankyshum/glean-mcp-server/releases
Project-URL: Documentation, https://github.com/alankyshum/glean-mcp-server#readme
Keywords: glean,mcp,model-context-protocol,search
Classifier: Programming Language :: Python :: 3
Classifier: Programming Language :: Python :: 3 :: Only
Classifier: Intended Audience :: Developers
Classifier: Topic :: Software Development :: Libraries
Classifier: Topic :: Internet :: WWW/HTTP :: Indexing/Search
Classifier: Operating System :: OS Independent
Classifier: Typing :: Typed
Requires-Python: >=3.9
License-File: LICENSE
Requires-Dist: httpx<0.28.0,>=0.25.0
Requires-Dist: pydantic<3,>=2.0.0
Requires-Dist: python-dotenv<2,>=1.0.0
Requires-Dist: mcp<2.0.0,>=1.10.0
Provides-Extra: dev
Requires-Dist: pytest<9,>=8.0; extra == "dev"
Requires-Dist: pytest-asyncio<0.24,>=0.23; extra == "dev"
Requires-Dist: ruff<0.6.0,>=0.5.0; extra == "dev"
Requires-Dist: build<2,>=1.2.0; extra == "dev"
Provides-Extra: perf
Requires-Dist: uvloop>=0.19.0; (platform_system == "Linux" or platform_system == "Darwin") and extra == "perf"
Dynamic: license-file
